{"machines":[{"id":1,"task_type_undertakes":"TYPE_A","machine_name":"","processing_time_constant":0.9743979608568015},{"id":2,"task_type_undertakes":"TYPE_A","machine_name":"","processing_time_constant":0.8103704927311566},{"id":3,"task_type_undertakes":"TYPE_B","machine_name":"","processing_time_constant":1.0198649911514837},{"id":4,"task_type_undertakes":"TYPE_B","machine_name":"","processing_time_constant":0.9741289570473107},{"id":5,"task_type_undertakes":"TYPE_C","machine_name":"","processing_time_constant":0.9681471208349957},{"id":6,"task_type_undertakes":"TYPE_C","machine_name":"","processing_time_constant":0.9321339284015496},{"id":7,"task_type_undertakes":"TYPE_D","machine_name":"","processing_time_constant":0.8818594536151371},{"id":8,"task_type_undertakes":"TYPE_D","machine_name":"","processing_time_constant":1.0477083865402654},{"id":9,"task_type_undertakes":"TYPE_E","machine_name":"","processing_time_constant":0.9198618694698093},{"id":10,"task_type_undertakes":"TYPE_E","machine_name":"","processing_time_constant":0.9067309100411467},{"id":11,"task_type_undertakes":"TYPE_F","machine_name":"","processing_time_constant":1.0484535331077178},{"id":12,"task_type_undertakes":"TYPE_F","machine_name":"","processing_time_constant":1.0116568377108157}],"jobs":[{"id":1,"deadline":25.623115124156474,"priority":"HIGH","tasks":[{"id":1,"type":"TYPE_B","processing_time":2.8262576592205475,"machines_can_undertake":[3,4],"preceding_task":-1,"succeeding_task":2,"scheduled_start_time":15.0,"scheduled_end_time":18.0,"scheduled_machine":3,"score":0},{"id":2,"type":"TYPE_E","processing_time":6,"machines_can_undertake":[9,10],"preceding_task":1,"succeeding_task":-1,"scheduled_start_time":18.0,"scheduled_end_time":23.0,"scheduled_machine":10,"score":0}]},{"id":2,"deadline":24.36027154884455,"priority":"HIGH","tasks":[{"id":3,"type":"TYPE_B","processing_time":9.936955780251397,"machines_can_undertake":[3,4],"preceding_task":-1,"succeeding_task":4,"scheduled_start_time":5.0,"scheduled_end_time":15.0,"scheduled_machine":3,"score":0},{"id":4,"type":"TYPE_D","processing_time":18,"machines_can_undertake":[7,8],"preceding_task":3,"succeeding_task":5,"scheduled_start_time":17.0,"scheduled_end_time":33.0,"scheduled_machine":7,"score":0},{"id":5,"type":"TYPE_F","processing_time":16,"machines_can_undertake":[11,12],"preceding_task":4,"succeeding_task":-1,"scheduled_start_time":33.0,"scheduled_end_time":49.0,"scheduled_machine":12,"score":0}]},{"id":3,"deadline":21.85013242696587,"priority":"HIGH","tasks":[{"id":6,"type":"TYPE_A","processing_time":12.544465365378253,"machines_can_undertake":[1,2],"preceding_task":-1,"succeeding_task":7,"scheduled_start_time":0.0,"scheduled_end_time":10.0,"scheduled_machine":2,"score":0},{"id":7,"type":"TYPE_D","processing_time":5,"machines_can_undertake":[7,8],"preceding_task":6,"succeeding_task":8,"scheduled_start_time":10.0,"scheduled_end_time":15.0,"scheduled_machine":8,"score":0},{"id":8,"type":"TYPE_E","processing_time":5,"machines_can_undertake":[9,10],"preceding_task":7,"succeeding_task":9,"scheduled_start_time":15.0,"scheduled_end_time":20.0,"scheduled_machine":9,"score":0},{"id":9,"type":"TYPE_F","processing_time":9,"machines_can_undertake":[11,12],"preceding_task":8,"succeeding_task":-1,"scheduled_start_time":20.0,"scheduled_end_time":29.0,"scheduled_machine":11,"score":0}]},{"id":4,"deadline":23.62357791989217,"priority":"HIGH","tasks":[{"id":10,"type":"TYPE_B","processing_time":9.674299801874193,"machines_can_undertake":[3,4],"preceding_task":-1,"succeeding_task":11,"scheduled_start_time":0.0,"scheduled_end_time":9.0,"scheduled_machine":4,"score":0},{"id":11,"type":"TYPE_D","processing_time":7,"machines_can_undertake":[7,8],"preceding_task":10,"succeeding_task":-1,"scheduled_start_time":15.0,"scheduled_end_time":22.0,"scheduled_machine":8,"score":0}]},{"id":5,"deadline":22.851370889795785,"priority":"HIGH","tasks":[{"id":12,"type":"TYPE_B","processing_time":5.249550854458863,"machines_can_undertake":[3,4],"preceding_task":-1,"succeeding_task":13,"scheduled_start_time":0.0,"scheduled_end_time":5.0,"scheduled_machine":3,"score":0},{"id":13,"type":"TYPE_D","processing_time":14,"machines_can_undertake":[7,8],"preceding_task":12,"succeeding_task":14,"scheduled_start_time":5.0,"scheduled_end_time":17.0,"scheduled_machine":7,"score":0},{"id":14,"type":"TYPE_E","processing_time":1,"machines_can_undertake":[9,10],"preceding_task":13,"succeeding_task":15,"scheduled_start_time":17.0,"scheduled_end_time":18.0,"scheduled_machine":10,"score":0},{"id":15,"type":"TYPE_F","processing_time":15,"machines_can_undertake":[11,12],"preceding_task":14,"succeeding_task":-1,"scheduled_start_time":18.0,"scheduled_end_time":33.0,"scheduled_machine":12,"score":0}]},{"id":6,"deadline":22.430558280126334,"priority":"HIGH","tasks":[{"id":16,"type":"TYPE_A","processing_time":8.043140425032282,"machines_can_undertake":[1,2],"preceding_task":-1,"succeeding_task":17,"scheduled_start_time":0.0,"scheduled_end_time":8.0,"scheduled_machine":1,"score":0},{"id":17,"type":"TYPE_C","processing_time":10,"machines_can_undertake":[5,6],"preceding_task":16,"succeeding_task":18,"scheduled_start_time":10.0,"scheduled_end_time":20.0,"scheduled_machine":5,"score":0},{"id":18,"type":"TYPE_D","processing_time":12,"machines_can_undertake":[7,8],"preceding_task":17,"succeeding_task":-1,"scheduled_start_time":22.0,"scheduled_end_time":35.0,"scheduled_machine":8,"score":0}]},{"id":7,"deadline":39.016402125998276,"priority":"MEDIUM","tasks":[{"id":19,"type":"TYPE_B","processing_time":7.891365248683275,"machines_can_undertake":[3,4],"preceding_task":-1,"succeeding_task":20,"scheduled_start_time":18.0,"scheduled_end_time":26.0,"scheduled_machine":3,"score":0},{"id":20,"type":"TYPE_E","processing_time":14,"machines_can_undertake":[9,10],"preceding_task":19,"succeeding_task":-1,"scheduled_start_time":26.0,"scheduled_end_time":39.0,"scheduled_machine":10,"score":0}]},{"id":8,"deadline":41.954590802611236,"priority":"MEDIUM","tasks":[{"id":21,"type":"TYPE_B","processing_time":10.247466662063959,"machines_can_undertake":[3,4],"preceding_task":-1,"succeeding_task":22,"scheduled_start_time":9.0,"scheduled_end_time":19.0,"scheduled_machine":4,"score":0},{"id":22,"type":"TYPE_C","processing_time":15,"machines_can_undertake":[5,6],"preceding_task":21,"succeeding_task":23,"scheduled_start_time":19.0,"scheduled_end_time":33.0,"scheduled_machine":6,"score":0},{"id":23,"type":"TYPE_E","processing_time":12,"machines_can_undertake":[9,10],"preceding_task":22,"succeeding_task":-1,"scheduled_start_time":33.0,"scheduled_end_time":44.0,"scheduled_machine":9,"score":0}]},{"id":9,"deadline":48.23239670501006,"priority":"MEDIUM","tasks":[{"id":24,"type":"TYPE_A","processing_time":6.7462329673091,"machines_can_undertake":[1,2],"preceding_task":-1,"succeeding_task":25,"scheduled_start_time":10.0,"scheduled_end_time":15.0,"scheduled_machine":2,"score":0},{"id":25,"type":"TYPE_B","processing_time":11,"machines_can_undertake":[3,4],"preceding_task":24,"succeeding_task":26,"scheduled_start_time":32.0,"scheduled_end_time":43.0,"scheduled_machine":4,"score":0},{"id":26,"type":"TYPE_D","processing_time":15,"machines_can_undertake":[7,8],"preceding_task":25,"succeeding_task":-1,"scheduled_start_time":43.0,"scheduled_end_time":56.0,"scheduled_machine":7,"score":0}]},{"id":10,"deadline":37.25031043327801,"priority":"MEDIUM","tasks":[{"id":27,"type":"TYPE_A","processing_time":1.2313472575834155,"machines_can_undertake":[1,2],"preceding_task":-1,"succeeding_task":28,"scheduled_start_time":24.0,"scheduled_end_time":25.0,"scheduled_machine":2,"score":0},{"id":28,"type":"TYPE_B","processing_time":11,"machines_can_undertake":[3,4],"preceding_task":27,"succeeding_task":29,"scheduled_start_time":26.0,"scheduled_end_time":37.0,"scheduled_machine":3,"score":0},{"id":29,"type":"TYPE_C","processing_time":10,"machines_can_undertake":[5,6],"preceding_task":28,"succeeding_task":30,"scheduled_start_time":37.0,"scheduled_end_time":46.0,"scheduled_machine":6,"score":0},{"id":30,"type":"TYPE_E","processing_time":1,"machines_can_undertake":[9,10],"preceding_task":29,"succeeding_task":-1,"scheduled_start_time":46.0,"scheduled_end_time":47.0,"scheduled_machine":9,"score":0}]},{"id":11,"deadline":42.68616559397616,"priority":"MEDIUM","tasks":[{"id":31,"type":"TYPE_A","processing_time":7.386998928831858,"machines_can_undertake":[1,2],"preceding_task":-1,"succeeding_task":32,"scheduled_start_time":8.0,"scheduled_end_time":15.0,"scheduled_machine":1,"score":0},{"id":32,"type":"TYPE_B","processing_time":13,"machines_can_undertake":[3,4],"preceding_task":31,"succeeding_task":33,"scheduled_start_time":19.0,"scheduled_end_time":32.0,"scheduled_machine":4,"score":0},{"id":33,"type":"TYPE_D","processing_time":8,"machines_can_undertake":[7,8],"preceding_task":32,"succeeding_task":34,"scheduled_start_time":33.0,"scheduled_end_time":40.0,"scheduled_machine":7,"score":0},{"id":34,"type":"TYPE_E","processing_time":10,"machines_can_undertake":[9,10],"preceding_task":33,"succeeding_task":-1,"scheduled_start_time":40.0,"scheduled_end_time":49.0,"scheduled_machine":10,"score":0}]},{"id":12,"deadline":40.48289937912344,"priority":"MEDIUM","tasks":[{"id":35,"type":"TYPE_A","processing_time":8.693699969947929,"machines_can_undertake":[1,2],"preceding_task":-1,"succeeding_task":36,"scheduled_start_time":26.0,"scheduled_end_time":33.0,"scheduled_machine":2,"score":0},{"id":36,"type":"TYPE_B","processing_time":14,"machines_can_undertake":[3,4],"preceding_task":35,"succeeding_task":-1,"scheduled_start_time":37.0,"scheduled_end_time":51.0,"scheduled_machine":3,"score":0}]},{"id":13,"deadline":71.74375674559228,"priority":"LOW","tasks":[{"id":37,"type":"TYPE_B","processing_time":11.504448094035864,"machines_can_undertake":[3,4],"preceding_task":-1,"succeeding_task":38,"scheduled_start_time":56.0,"scheduled_end_time":68.0,"scheduled_machine":3,"score":0},{"id":38,"type":"TYPE_C","processing_time":10,"machines_can_undertake":[5,6],"preceding_task":37,"succeeding_task":39,"scheduled_start_time":68.0,"scheduled_end_time":77.0,"scheduled_machine":6,"score":0},{"id":39,"type":"TYPE_E","processing_time":7,"machines_can_undertake":[9,10],"preceding_task":38,"succeeding_task":-1,"scheduled_start_time":77.0,"scheduled_end_time":83.0,"scheduled_machine":9,"score":0}]},{"id":14,"deadline":53.19480337640187,"priority":"LOW","tasks":[{"id":40,"type":"TYPE_B","processing_time":12.715206826003891,"machines_can_undertake":[3,4],"preceding_task":-1,"succeeding_task":41,"scheduled_start_time":56.0,"scheduled_end_time":68.0,"scheduled_machine":4,"score":0},{"id":41,"type":"TYPE_F","processing_time":8,"machines_can_undertake":[11,12],"preceding_task":40,"succeeding_task":-1,"scheduled_start_time":68.0,"scheduled_end_time":76.0,"scheduled_machine":11,"score":0}]},{"id":15,"deadline":64.84901568843861,"priority":"LOW","tasks":[{"id":42,"type":"TYPE_A","processing_time":11.403553976350985,"machines_can_undertake":[1,2],"preceding_task":-1,"succeeding_task":43,"scheduled_start_time":15.0,"scheduled_end_time":24.0,"scheduled_machine":2,"score":0},{"id":43,"type":"TYPE_C","processing_time":4,"machines_can_undertake":[5,6],"preceding_task":42,"succeeding_task":44,"scheduled_start_time":24.0,"scheduled_end_time":28.0,"scheduled_machine":5,"score":0},{"id":44,"type":"TYPE_F","processing_time":10,"machines_can_undertake":[11,12],"preceding_task":43,"succeeding_task":-1,"scheduled_start_time":29.0,"scheduled_end_time":39.0,"scheduled_machine":11,"score":0}]},{"id":16,"deadline":50.87909221427446,"priority":"LOW","tasks":[{"id":45,"type":"TYPE_A","processing_time":9.371166941797085,"machines_can_undertake":[1,2],"preceding_task":-1,"succeeding_task":46,"scheduled_start_time":33.0,"scheduled_end_time":41.0,"scheduled_machine":2,"score":0},{"id":46,"type":"TYPE_B","processing_time":13,"machines_can_undertake":[3,4],"preceding_task":45,"succeeding_task":47,"scheduled_start_time":43.0,"scheduled_end_time":56.0,"scheduled_machine":4,"score":0},{"id":47,"type":"TYPE_C","processing_time":19,"machines_can_undertake":[5,6],"preceding_task":46,"succeeding_task":-1,"scheduled_start_time":56.0,"scheduled_end_time":74.0,"scheduled_machine":5,"score":0}]},{"id":17,"deadline":59.481462024570234,"priority":"LOW","tasks":[{"id":48,"type":"TYPE_B","processing_time":13.363970495115067,"machines_can_undertake":[3,4],"preceding_task":-1,"succeeding_task":49,"scheduled_start_time":68.0,"scheduled_end_time":81.0,"scheduled_machine":4,"score":0},{"id":49,"type":"TYPE_D","processing_time":8,"machines_can_undertake":[7,8],"preceding_task":48,"succeeding_task":-1,"scheduled_start_time":81.0,"scheduled_end_time":88.0,"scheduled_machine":7,"score":0}]},{"id":18,"deadline":63.47700966777594,"priority":"LOW","tasks":[{"id":50,"type":"TYPE_A","processing_time":20.341179472258197,"machines_can_undertake":[1,2],"preceding_task":-1,"succeeding_task":51,"scheduled_start_time":15.0,"scheduled_end_time":35.0,"scheduled_machine":1,"score":0},{"id":51,"type":"TYPE_D","processing_time":8,"machines_can_undertake":[7,8],"preceding_task":50,"succeeding_task":52,"scheduled_start_time":35.0,"scheduled_end_time":43.0,"scheduled_machine":8,"score":0},{"id":52,"type":"TYPE_F","processing_time":7,"machines_can_undertake":[11,12],"preceding_task":51,"succeeding_task":-1,"scheduled_start_time":43.0,"scheduled_end_time":50.0,"scheduled_machine":11,"score":0}]},{"id":19,"deadline":57.79458244257821,"priority":"LOW","tasks":[{"id":53,"type":"TYPE_B","processing_time":14.182098105737936,"machines_can_undertake":[3,4],"preceding_task":-1,"succeeding_task":54,"scheduled_start_time":68.0,"scheduled_end_time":82.0,"scheduled_machine":3,"score":0},{"id":54,"type":"TYPE_C","processing_time":10,"machines_can_undertake":[5,6],"preceding_task":53,"succeeding_task":-1,"scheduled_start_time":82.0,"scheduled_end_time":91.0,"scheduled_machine":6,"score":0}]},{"id":20,"deadline":51.65845228827175,"priority":"LOW","tasks":[{"id":55,"type":"TYPE_A","processing_time":12.66367447356246,"machines_can_undertake":[1,2],"preceding_task":-1,"succeeding_task":56,"scheduled_start_time":35.0,"scheduled_end_time":47.0,"scheduled_machine":1,"score":0},{"id":56,"type":"TYPE_B","processing_time":5,"machines_can_undertake":[3,4],"preceding_task":55,"succeeding_task":57,"scheduled_start_time":51.0,"scheduled_end_time":56.0,"scheduled_machine":3,"score":0},{"id":57,"type":"TYPE_D","processing_time":12,"machines_can_undertake":[7,8],"preceding_task":56,"succeeding_task":58,"scheduled_start_time":56.0,"scheduled_end_time":67.0,"scheduled_machine":7,"score":0},{"id":58,"type":"TYPE_E","processing_time":6,"machines_can_undertake":[9,10],"preceding_task":57,"succeeding_task":-1,"scheduled_start_time":67.0,"scheduled_end_time":72.0,"scheduled_machine":10,"score":0}]}]}
